JavaForSmallTeams/README.md
JavaForSmallTeams/__init__.py
JavaForSmallTeams/__main__.py
JavaForSmallTeams/file.epub
JavaForSmallTeams/index.html
JavaForSmallTeams/css/__init__.py
JavaForSmallTeams/css/annotations.css
JavaForSmallTeams/css/main.css
JavaForSmallTeams/css/normalize.css
JavaForSmallTeams/css/popup.css
JavaForSmallTeams/font/__init__.py
JavaForSmallTeams/font/fontello.eot
JavaForSmallTeams/font/fontello.svg
JavaForSmallTeams/font/fontello.ttf
JavaForSmallTeams/font/fontello.woff
JavaForSmallTeams/img/__init__.py
JavaForSmallTeams/img/annotator-glyph-sprite.png
JavaForSmallTeams/img/annotator-icon-sprite.png
JavaForSmallTeams/img/apple-touch-icon.png
JavaForSmallTeams/img/cancelfullscreen.png
JavaForSmallTeams/img/close.png
JavaForSmallTeams/img/fullscreen.png
JavaForSmallTeams/img/loader.gif
JavaForSmallTeams/img/menu-icon.png
JavaForSmallTeams/img/save.png
JavaForSmallTeams/img/saved.png
JavaForSmallTeams/img/settings-s.png
JavaForSmallTeams/img/settings.png
JavaForSmallTeams/img/star.png
JavaForSmallTeams/js/__init__.py
JavaForSmallTeams/js/epub.js
JavaForSmallTeams/js/epub.min.js
JavaForSmallTeams/js/epub.min.map
JavaForSmallTeams/js/hooks.min.js
JavaForSmallTeams/js/hooks.min.map
JavaForSmallTeams/js/reader.js
JavaForSmallTeams/js/reader.js.map
JavaForSmallTeams/js/reader.min.js
JavaForSmallTeams/js/reader.min.map
JavaForSmallTeams/js/hooks/__init__.py
JavaForSmallTeams/js/hooks/extensions/__init__.py
JavaForSmallTeams/js/hooks/extensions/highlight.js
JavaForSmallTeams/js/libs/__init__.py
JavaForSmallTeams/js/libs/jquery.min.js
JavaForSmallTeams/js/libs/localforage.min.js
JavaForSmallTeams/js/libs/screenfull.js
JavaForSmallTeams/js/libs/screenfull.min.js
JavaForSmallTeams/js/libs/zip.min.js
JavaForSmallTeams/js/plugins/__init__.py
JavaForSmallTeams/js/plugins/hypothesis.js
JavaForSmallTeams/js/plugins/search.js
java_for_small_teams-2024.3.2.0.dist-info/METADATA
java_for_small_teams-2024.3.2.0.dist-info/WHEEL
java_for_small_teams-2024.3.2.0.dist-info/entry_points.txt
java_for_small_teams-2024.3.2.0.dist-info/top_level.txt
java_for_small_teams-2024.3.2.0.dist-info/RECORD
